<?xml version="1.0" encoding="UTF-8"?>
<entry xmlns="http://www.w3.org/2005/Atom">
<id>fr.univmobile:unm-backend:test/pois/002:poi1799_1</id>
<link rel="self" href="fr.univmobile:unm-backend:test/pois/002:poi1799_1.xml"/>
<title>BU d'histoire</title>
<updated>2014-08-15T01:46:51.003+02:00</updated>
<category term="pois"/>
<author>
	<name>dandriana</name>
	<uri>fr.univmobile:unm-backend:test/users:dandriana</uri>
</author>
<content uid="1799"
	coordinates="48.901822486358,2.212441563"
	active="true"
	markerType="point"
	createdAt="2011-04-05T16:17:45.000+02:00"
	updatedAt="2011-11-15T16:24:37.000+01:00"
	createdBy="Marine Gianfermi Paris X"
	updatedBy="Marine Gianfermi Paris X"
	parentUid="2499"
	name="BU d'histoire">
	<poiType id="5" label="Bibliothèque" categoryId="9" categoryLabel="Bibliothèque Universitaire"/>
	<address>
		<floor>Rdc </floor>
		<openingHours>Du lundi au jeudi :
9h / 17h</openingHours>
	</address>
</content>
</entry>
