<?xml version="1.0" encoding="UTF-8"?>
<entry xmlns="http://www.w3.org/2005/Atom">
<id>fr.univmobile:unm-backend:test/pois/002:poi1847_1</id>
<link rel="self" href="fr.univmobile:unm-backend:test/pois/002:poi1847_1.xml"/>
<title>La sandwicherie</title>
<updated>2014-08-15T01:46:51.478+02:00</updated>
<category term="pois"/>
<author>
	<name>dandriana</name>
	<uri>fr.univmobile:unm-backend:test/users:dandriana</uri>
</author>
<content uid="1847"
	coordinates="48.902475363144,2.21449747681"
	active="true"
	markerType="point"
	createdAt="2011-04-05T17:19:56.000+02:00"
	updatedAt="2012-01-06T12:50:05.000+01:00"
	createdBy="Marine Gianfermi Paris X"
	updatedBy="Marine Gianfermi Paris X"
	parentUid="2491"
	name="La sandwicherie">
	<poiType id="15" label="Cafétéria" categoryId="4" categoryLabel="Restauration Universitaire"/>
	<address>
		<floor>Rdc</floor>
		<openingHours>Du lundi au vendredi :
8h / 18h
Samedi : 
8h30 / 12h30</openingHours>
	</address>
</content>
</entry>
