<?xml version="1.0" encoding="UTF-8"?>
<entry xmlns="http://www.w3.org/2005/Atom">
<id>fr.univmobile:unm-backend:test/pois/002:poi4117_1</id>
<link rel="self" href="fr.univmobile:unm-backend:test/pois/002:poi4117_1.xml"/>
<title>Polygone </title>
<updated>2014-08-15T01:47:13.859+02:00</updated>
<category term="pois"/>
<author>
	<name>dandriana</name>
	<uri>fr.univmobile:unm-backend:test/users:dandriana</uri>
</author>
<content uid="4117"
	coordinates="48.633622444757,2.4684416502714|48.633553313478,2.4685221165419|48.6334735465,2.4683799594641|48.633443412276,2.4684121459723|48.633475319101,2.4684765189886|48.63342391365,2.4685247987509|48.633361872519,2.4683799594641|48.633427458855,2.4682968109846|48.633354782099,2.4681573361158|48.633315784772,2.468194887042|48.633204110442,2.4679508060217|48.633234244809,2.4679213017225|48.633145614265,2.4677389115095|48.633120797685,2.4677657335997|48.633143841653,2.4678006023169|48.633104844163,2.4678515642881|48.633028621709,2.4677147716284|48.633064074028,2.4676638096571|48.633095981093,2.4677255004644|48.633122570299,2.4676933139563|48.63304280264,2.4675431102514|48.633009122923,2.4675833433867|48.633028621709,2.4676074832678|48.633000259836,2.4676369875669|48.632959489617,2.4675860255957|48.633028621709,2.4675162881613|48.633010895541,2.4674760550261|48.633101298935,2.4673714488745|48.633152704715,2.467470690608|48.633337056045,2.4672319740057|48.633523179301,2.4670093506575|48.633579902443,2.4671193212271|48.633484182104,2.4672185629606|48.633622444757,2.4674787372351|48.63354090529,2.4675806611776|48.63341150543,2.4673312157393|48.633390234188,2.4673446267843|48.63340086981,2.4673768132925|48.633223609152,2.4676155298948|48.633333510834,2.4678488820791|48.633517861503,2.4676021188498|48.633767797394,2.4673070758581|48.633883015649,2.4675377458334|48.633735890753,2.4677281826735|48.633434549265,2.4680500477552|48.63356040387,2.4683048576117|48.633819202494,2.4677845090628|48.63389719634,2.4678837507963|48.633622444757,2.4684416502714"
	active="true"
	markerType="polygon"
	createdAt="2011-05-18T16:31:05.000+02:00"
	updatedAt="2013-06-26T11:02:25.000+02:00"
	deletedAt="2011-06-03T15:23:22.000+02:00"
	createdBy="Abdul Aziz Sao"
	updatedBy="yasmine"
	name="Polygone ">
	<poiType id="32" label="Polygone" categoryId="1" categoryLabel="Plans"/>
</content>
</entry>
