<?xml version="1.0" encoding="UTF-8"?>
<entry xmlns="http://www.w3.org/2005/Atom">
<id>fr.univmobile:unm-backend:test/pois/002:poi5197_1</id>
<link rel="self" href="fr.univmobile:unm-backend:test/pois/002:poi5197_1.xml"/>
<title>ISSB</title>
<updated>2014-08-15T01:47:24.191+02:00</updated>
<category term="pois"/>
<author>
	<name>dandriana</name>
	<uri>fr.univmobile:unm-backend:test/users:dandriana</uri>
</author>
<content uid="5197"
	coordinates="48.618346237079,2.4503441154957"
	active="true"
	markerType="point"
	createdAt="2011-05-31T16:52:52.000+02:00"
	updatedAt="2011-06-15T17:20:53.000+02:00"
	createdBy="Marine Gianfermi Paris X"
	updatedBy="Marine Gianfermi Paris X"
	parentUid="3024"
	name="ISSB">
	<poiType id="18" label="Institut" categoryId="22" categoryLabel="Institut &amp; École"/>
	<description>Institut de Biologie Systémique et Synthétique</description>
	<address>
		<phone>01 69 47 44 30</phone>
		<email>sylvie.bobelet@issb.genopole.fr</email>
	</address>
</content>
</entry>
