<?xml version="1.0" encoding="UTF-8"?>
<entry xmlns="http://www.w3.org/2005/Atom">
<id>fr.univmobile:unm-backend:test/pois/002:poi5728_1</id>
<link rel="self" href="fr.univmobile:unm-backend:test/pois/002:poi5728_1.xml"/>
<title>Amphithéâtres 1 &amp; 2</title>
<updated>2014-08-15T01:47:29.372+02:00</updated>
<category term="pois"/>
<author>
	<name>dandriana</name>
	<uri>fr.univmobile:unm-backend:test/users:dandriana</uri>
</author>
<content uid="5728"
	coordinates="48.781939064977,2.2860400378704"
	active="true"
	markerType="point"
	createdAt="2011-06-08T14:46:39.000+02:00"
	updatedAt="2011-07-05T09:20:02.000+02:00"
	createdBy="j.richer"
	updatedBy="j.richer"
	parentUid="4666"
	name="Amphithéâtres 1 &amp; 2">
	<poiType id="11" label="Amphithéâtre" categoryId="3" categoryLabel="Amphithéâtre "/>
	<address>
		<fax>test</fax>
	</address>
</content>
</entry>
