<?xml version="1.0" encoding="UTF-8"?>
<entry xmlns="http://www.w3.org/2005/Atom">
<id>fr.univmobile:unm-backend:test/pois/002:poi5321_1</id>
<link rel="self" href="fr.univmobile:unm-backend:test/pois/002:poi5321_1.xml"/>
<title>Physique-Chimie-Sciences de la terre (L1 PCST)</title>
<updated>2014-08-15T01:47:25.130+02:00</updated>
<category term="pois"/>
<author>
	<name>dandriana</name>
	<uri>fr.univmobile:unm-backend:test/users:dandriana</uri>
</author>
<content uid="5321"
	coordinates="48.70132790072,2.166552990675"
	active="true"
	markerType="point"
	createdAt="2011-06-01T14:04:03.000+02:00"
	updatedAt="2011-07-06T15:47:00.000+02:00"
	createdBy="j.richer"
	updatedBy="j.richer"
	parentUid="4583"
	name="Physique-Chimie-Sciences de la terre (L1 PCST)">
	<poiType id="17" label="Formation" categoryId="17" categoryLabel="Formation"/>
	<address>
		<floor>Bâtiment 333, bureau 116</floor>
		<url>http://www.u-psud.fr/fr/les_formations/les_formations_par_diplome/licences/sciences_technologies_sante/pcst.html</url>
		<phone>01 69 15 79 04</phone>
		<fax>01 69 15 54 43</fax>
		<email>nadia.er-rajfi@u-psud.fr</email>
	</address>
</content>
</entry>
