<?xml version="1.0" encoding="UTF-8"?>
<entry xmlns="http://www.w3.org/2005/Atom">
<id>fr.univmobile:unm-backend:test/pois/002:poi6657_1</id>
<link rel="self" href="fr.univmobile:unm-backend:test/pois/002:poi6657_1.xml"/>
<title>Brasserie Neuville II</title>
<updated>2014-08-15T01:47:39.052+02:00</updated>
<category term="pois"/>
<author>
	<name>dandriana</name>
	<uri>fr.univmobile:unm-backend:test/users:dandriana</uri>
</author>
<content uid="6657"
	coordinates="49.017530239312,2.0739108324051"
	active="true"
	markerType="point"
	createdAt="2011-07-20T14:47:05.000+02:00"
	updatedAt="2011-09-02T16:08:40.000+02:00"
	createdBy="d.rasse"
	updatedBy="d.rasse"
	parentUid="6653"
	name="Brasserie Neuville II">
	<poiType id="15" label="Cafétéria" categoryId="4" categoryLabel="Restauration Universitaire"/>
	<address>
		<openingHours>De 11h30 à 13h30</openingHours>
	</address>
</content>
</entry>
