<?xml version="1.0" encoding="UTF-8"?>
<entry xmlns="http://www.w3.org/2005/Atom">
<id>fr.univmobile:unm-backend:test/pois/002:poi6194_1</id>
<link rel="self" href="fr.univmobile:unm-backend:test/pois/002:poi6194_1.xml"/>
<title>Ateliers artistiques</title>
<updated>2014-08-15T01:47:34.782+02:00</updated>
<category term="pois"/>
<author>
	<name>dandriana</name>
	<uri>fr.univmobile:unm-backend:test/users:dandriana</uri>
</author>
<content uid="6194"
	coordinates="48.624054750259,2.4270048737526"
	active="true"
	markerType="point"
	createdAt="2011-06-15T17:30:00.000+02:00"
	updatedAt="2011-06-15T17:31:01.000+02:00"
	createdBy="Abdul Aziz Sao"
	updatedBy="Abdul Aziz Sao"
	parentUid="256"
	name="Ateliers artistiques">
	<poiType id="24" label="Culture" categoryId="16" categoryLabel="Culture"/>
	<description>Responsable : Maria MUNIER</description>
	<address>
		<floor>Bâtiment Ile-de-France – Rez-de-Chaussée – Bureau 41 ou 43</floor>
		<phone>01 69 47 70 30</phone>
		<email>maria.munier@univ-evry.fr</email>
	</address>
</content>
</entry>
