<?xml version="1.0" encoding="UTF-8"?>
<entry xmlns="http://www.w3.org/2005/Atom">
<id>fr.univmobile:unm-backend:test/pois/002:poi6383_1</id>
<link rel="self" href="fr.univmobile:unm-backend:test/pois/002:poi6383_1.xml"/>
<title>Sociologie (M2 Migrations et relations interethniques)</title>
<updated>2014-08-15T01:47:36.654+02:00</updated>
<category term="pois"/>
<author>
	<name>dandriana</name>
	<uri>fr.univmobile:unm-backend:test/users:dandriana</uri>
</author>
<content uid="6383"
	coordinates="48.825617823899,2.3665314540267"
	active="true"
	markerType="point"
	createdAt="2011-06-22T16:03:46.000+02:00"
	updatedAt="2011-06-24T16:06:51.000+02:00"
	createdBy="j.richer"
	updatedBy="j.richer"
	parentUid="1772"
	name="Sociologie (M2 Migrations et relations interethniques)">
	<poiType id="17" label="Formation" categoryId="17" categoryLabel="Formation"/>
	<description>Master : Sociologie et anthropologie : politique, culture et migrations
Spécialité Recherche et Professionnel : Migrations et relations interethniques</description>
	<address>
		<floor>Les Olympiades Immeuble Montréal - 3ème étage, bureau 318</floor>
		<url>http://www.univ-paris-diderot.fr/sc/site.php?bc=formations&amp;np=SPECIALITE?NS=845</url>
		<phone>01 57 27 64 83</phone>
		<fax>01 57 27 64 91</fax>
		<email>urmis@univ-paris-diderot.fr</email>
	</address>
</content>
</entry>
